soiree/__init__.py
soiree/module.MD
soiree/module.s.HTML
soiree/names.s.HTML
soiree/procedure.proc.py
soiree/__book/codesweeper--ai-generated-8311435_1920.jpg
soiree/__book/codesweeper--ai-generated-8311446_1920.jpg
soiree/__book/codesweeper--ai-generated-8311450_1920.jpg
soiree/__license/license.s.HTML
soiree/__license/options/gpl-3.0-standalone.html
soiree/_clique/__init__.py
soiree/_clique/group/__init__.py
soiree/_status/__init__.py
soiree/_status/status.proc.py
soiree/_status/_stories/story_instrument_1/status_1.py
soiree/instrument/__init__.py
soiree/instrument/module--names.s.HTML
soiree/instrument/start.proc.py
soiree/instrument/__agenda/agenda.s.HTML
soiree/instrument/__book/TheDigitalArtist--ai-generated-8228359_1920.jpg
soiree/instrument/__book/TheDigitalArtist--ai-generated-8228360_1920.jpg
soiree/instrument/__book/dlsdkcgl--hidden-8315722_1920.jpg
soiree/instrument/__book/_hardware/hardware.s.HTML
soiree/instrument/__book/_hardware/ISO/ISO_lab.s.HTML
soiree/instrument/__book/_hardware/ISO/ISO_lab_2.s.HTML
soiree/instrument/__book/_hardware/ISO/write_ISO_to_drive.py
soiree/instrument/__book/_hardware/docker/docker.s.HTML
soiree/instrument/__book/_hardware/docker/essential_installations.s.HTML
soiree/instrument/__book/_hardware/docker/compose/compose.s.HTML
soiree/instrument/__book/_hardware/docker/containers/containers.s.HTML
soiree/instrument/__book/_hardware/docker/containers/installations.s.HTML
soiree/instrument/__book/_hardware/docker/images/images.s.HTML
soiree/instrument/_status/status_1.py
soiree/instrument/climate/__init__.py
soiree/instrument/clique/__init__.py
soiree/instrument/frontend/codesweeper--ai-generated-8311446_1920.jpg
soiree/instrument/frontend/index.html
soiree/instrument/frontend/assets/feel-1b84c382.js
soiree/instrument/frontend/assets/futon-180affc4.js
soiree/instrument/frontend/assets/index-d4db3b65.js
soiree/instrument/frontend/assets/index-f1fd6021.css
soiree/instrument/frontend/assets/perform-9529be50.js
soiree-1.0.0.dist-info/METADATA
soiree-1.0.0.dist-info/WHEEL
soiree-1.0.0.dist-info/entry_points.txt
soiree-1.0.0.dist-info/top_level.txt
soiree-1.0.0.dist-info/RECORD
